adaline.py
adaline-0.1.0.dist-info/METADATA
adaline-0.1.0.dist-info/WHEEL
adaline-0.1.0.dist-info/top_level.txt
adaline-0.1.0.dist-info/RECORD
