Metadata-Version: 2.4
Name: adaline
Version: 0.1.0
Summary: Adaline implementation.
Requires-Python: >=3.13
